demo/__init__.py
demo/pubsub_stream.py
demo/show_ha_stream_async.py
demo/show_stream.py
demo/show_stream_async.py
dnaStreaming/__init__.py
dnaStreaming/config.py
dnaStreaming/customer_config.json
dnaStreaming/listener.py
dnaStreaming/services/__init__.py
dnaStreaming/services/authentication_service.py
dnaStreaming/services/availability_service.py
dnaStreaming/services/credentials_service.py
dnaStreaming/services/pubsub_service.py
dnaStreaming/test/__init__.py
dnaStreaming/test/test_config.py
dnastreaming-2.3.1.dist-info/LICENSE
dnastreaming-2.3.1.dist-info/METADATA
dnastreaming-2.3.1.dist-info/WHEEL
dnastreaming-2.3.1.dist-info/top_level.txt
dnastreaming-2.3.1.dist-info/RECORD
