Metadata-Version: 2.1
Name: dnaStreaming
Version: 2.3.1
Summary: Dow Jones DNA Streaming Project
Home-page: https://github.com/dowjones/dj-dna-streams-python
Download-URL: https://github.com/dowjones/dj-dna-streams-python/archive/release-2.3.1.tar.gz
Author: Zachary Kagan
Author-email: zachary.kagan@dowjones.com
License: MIT
Keywords: DOWJONES,FACTIVA,STREAMS
Classifier: Development Status :: 5 - Production/Stable
Classifier: Intended Audience :: Developers
Classifier: License :: OSI Approved :: MIT License
Classifier: Programming Language :: Python :: 3
License-File: LICENSE
Requires-Dist: setuptools >=75.1.0
Requires-Dist: googleapis-common-protos >=1.56.4
Requires-Dist: google-auth >=2.11.0
Requires-Dist: google-cloud-pubsub ==2.13.6
Requires-Dist: google-cloud-core ==2.3.2
Requires-Dist: google-api-core ==2.10.1
Requires-Dist: mock >=3.0.5
Requires-Dist: oauth2client >=4.1.3
Requires-Dist: requests >=2.28.0
